{
  "annotations": {
    "list": [
      {
        "builtIn": 1,
        "datasource": {
          "type": "grafana",
          "uid": "-- Grafana --"
        },
        "enable": true,
        "hide": true,
        "iconColor": "rgba(0, 211, 255, 1)",
        "name": "Annotations & Alerts",
        "target": {
          "limit": 100,
          "matchAny": false,
          "tags": [],
          "type": "dashboard"
        },
        "type": "dashboard"
      }
    ]
  },
  "editable": true,
  "fiscalYearStartMonth": 0,
  "graphTooltip": 0,
  "id": 52,
  "links": [],
  "liveNow": false,
  "panels": [
    {
      "collapsed": false,
      "gridPos": {
        "h": 1,
        "w": 24,
        "x": 0,
        "y": 0
      },
      "id": 22,
      "panels": [],
      "title": "Host Details",
      "type": "row"
    },
    {
      "datasource": {
        "type": "prometheus",
        "uid": "Beh5B5B4z"
      },
      "fieldConfig": {
        "defaults": {
          "color": {
            "mode": "palette-classic"
          },
          "custom": {
            "axisCenteredZero": false,
            "axisColorMode": "text",
            "axisLabel": "",
            "axisPlacement": "auto",
            "barAlignment": 0,
            "drawStyle": "line",
            "fillOpacity": 0,
            "gradientMode": "none",
            "hideFrom": {
              "legend": false,
              "tooltip": false,
              "viz": false
            },
            "lineInterpolation": "linear",
            "lineWidth": 1,
            "pointSize": 5,
            "scaleDistribution": {
              "type": "linear"
            },
            "showPoints": "auto",
            "spanNulls": false,
            "stacking": {
              "group": "A",
              "mode": "none"
            },
            "thresholdsStyle": {
              "mode": "off"
            }
          },
          "mappings": [],
          "thresholds": {
            "mode": "absolute",
            "steps": [
              {
                "color": "green",
                "value": null
              },
              {
                "color": "red",
                "value": 80
              }
            ]
          }
        },
        "overrides": []
      },
      "gridPos": {
        "h": 11,
        "w": 18,
        "x": 0,
        "y": 1
      },
      "id": 10,
      "options": {
        "legend": {
          "calcs": [],
          "displayMode": "list",
          "placement": "bottom",
          "showLegend": true
        },
        "tooltip": {
          "mode": "single",
          "sort": "none"
        }
      },
      "targets": [
        {
          "datasource": {
            "type": "prometheus",
            "uid": "Beh5B5B4z"
          },
          "editorMode": "code",
          "expr": "planetary_VSphere_vmware_power_power_average{host=\"${instance}\", type=\"host\", job=\"local-energy-col-erlc-http\"}",
          "hide": false,
          "legendFormat": "__auto",
          "range": true,
          "refId": "B"
        },
        {
          "datasource": {
            "type": "prometheus",
            "uid": "Beh5B5B4z"
          },
          "editorMode": "code",
          "expr": "planetary_DellOpenManage_dell_openmanage_power{host=\"${instance}\"} offset 60m",
          "hide": false,
          "legendFormat": "__auto",
          "range": true,
          "refId": "A"
        }
      ],
      "title": "Vsphere Host vs Dell OME Power",
      "type": "timeseries"
    },
    {
      "datasource": {
        "type": "prometheus",
        "uid": "Beh5B5B4z"
      },
      "fieldConfig": {
        "defaults": {
          "color": {
            "mode": "palette-classic"
          },
          "custom": {
            "axisCenteredZero": false,
            "axisColorMode": "text",
            "axisLabel": "",
            "axisPlacement": "auto",
            "barAlignment": 0,
            "drawStyle": "line",
            "fillOpacity": 0,
            "gradientMode": "none",
            "hideFrom": {
              "legend": false,
              "tooltip": false,
              "viz": false
            },
            "lineInterpolation": "linear",
            "lineWidth": 1,
            "pointSize": 5,
            "scaleDistribution": {
              "type": "linear"
            },
            "showPoints": "auto",
            "spanNulls": false,
            "stacking": {
              "group": "A",
              "mode": "none"
            },
            "thresholdsStyle": {
              "mode": "off"
            }
          },
          "mappings": [],
          "thresholds": {
            "mode": "absolute",
            "steps": [
              {
                "color": "green",
                "value": null
              },
              {
                "color": "red",
                "value": 80
              }
            ]
          }
        },
        "overrides": []
      },
      "gridPos": {
        "h": 13,
        "w": 9,
        "x": 0,
        "y": 12
      },
      "id": 6,
      "options": {
        "legend": {
          "calcs": [],
          "displayMode": "list",
          "placement": "bottom",
          "showLegend": true
        },
        "tooltip": {
          "mode": "single",
          "sort": "none"
        }
      },
      "targets": [
        {
          "datasource": {
            "type": "prometheus",
            "uid": "Beh5B5B4z"
          },
          "editorMode": "code",
          "expr": "planetary_VSphere_vmware_power_power_average{host=\"${instance}\", type=\"host\", job=\"local-energy-col-erlc-http\"}",
          "legendFormat": "__auto",
          "range": true,
          "refId": "A"
        },
        {
          "datasource": {
            "type": "prometheus",
            "uid": "Beh5B5B4z"
          },
          "editorMode": "code",
          "expr": "sum(planetary_VSphere_vmware_power_power_average{host=\"${instance}\", type=\"vm\", job=\"local-energy-col-erlc-http\"}) / 1000 + ${hostPowerOffset}",
          "hide": false,
          "legendFormat": "__auto",
          "range": true,
          "refId": "B"
        }
      ],
      "title": "Vsphere Host vs VM Power Offset ${hostPowerOffset}",
      "type": "timeseries"
    },
    {
      "datasource": {
        "type": "prometheus",
        "uid": "Beh5B5B4z"
      },
      "fieldConfig": {
        "defaults": {
          "color": {
            "mode": "palette-classic"
          },
          "custom": {
            "axisCenteredZero": false,
            "axisColorMode": "text",
            "axisLabel": "",
            "axisPlacement": "auto",
            "barAlignment": 0,
            "drawStyle": "line",
            "fillOpacity": 25,
            "gradientMode": "none",
            "hideFrom": {
              "legend": false,
              "tooltip": false,
              "viz": false
            },
            "lineInterpolation": "linear",
            "lineWidth": 1,
            "pointSize": 5,
            "scaleDistribution": {
              "type": "linear"
            },
            "showPoints": "auto",
            "spanNulls": false,
            "stacking": {
              "group": "A",
              "mode": "normal"
            },
            "thresholdsStyle": {
              "mode": "off"
            }
          },
          "mappings": [],
          "thresholds": {
            "mode": "absolute",
            "steps": [
              {
                "color": "green",
                "value": null
              },
              {
                "color": "red",
                "value": 80
              }
            ]
          }
        },
        "overrides": []
      },
      "gridPos": {
        "h": 13,
        "w": 9,
        "x": 9,
        "y": 12
      },
      "id": 7,
      "options": {
        "legend": {
          "calcs": [],
          "displayMode": "list",
          "placement": "bottom",
          "showLegend": true
        },
        "tooltip": {
          "mode": "single",
          "sort": "none"
        }
      },
      "pluginVersion": "9.4.7",
      "targets": [
        {
          "datasource": {
            "type": "prometheus",
            "uid": "Beh5B5B4z"
          },
          "editorMode": "code",
          "expr": "planetary_VSphere_vmware_power_power_average{host=\"${instance}\", type=\"vm\", job=\"local-energy-col-erlc-http\"} / 1000",
          "hide": false,
          "legendFormat": "__auto",
          "range": true,
          "refId": "B"
        }
      ],
      "title": "Vsphere VMs Power",
      "type": "timeseries"
    },
    {
      "datasource": {
        "type": "prometheus",
        "uid": "Beh5B5B4z"
      },
      "fieldConfig": {
        "defaults": {
          "color": {
            "mode": "palette-classic"
          },
          "custom": {
            "axisCenteredZero": false,
            "axisColorMode": "text",
            "axisLabel": "",
            "axisPlacement": "auto",
            "barAlignment": 0,
            "drawStyle": "line",
            "fillOpacity": 0,
            "gradientMode": "none",
            "hideFrom": {
              "legend": false,
              "tooltip": false,
              "viz": false
            },
            "lineInterpolation": "linear",
            "lineWidth": 1,
            "pointSize": 5,
            "scaleDistribution": {
              "type": "linear"
            },
            "showPoints": "auto",
            "spanNulls": false,
            "stacking": {
              "group": "A",
              "mode": "none"
            },
            "thresholdsStyle": {
              "mode": "off"
            }
          },
          "mappings": [],
          "thresholds": {
            "mode": "absolute",
            "steps": [
              {
                "color": "green"
              },
              {
                "color": "red",
                "value": 80
              }
            ]
          }
        },
        "overrides": []
      },
      "gridPos": {
        "h": 12,
        "w": 9,
        "x": 0,
        "y": 25
      },
      "id": 9,
      "options": {
        "legend": {
          "calcs": [],
          "displayMode": "list",
          "placement": "bottom",
          "showLegend": true
        },
        "tooltip": {
          "mode": "single",
          "sort": "none"
        }
      },
      "targets": [
        {
          "datasource": {
            "type": "prometheus",
            "uid": "Beh5B5B4z"
          },
          "editorMode": "code",
          "expr": "planetary_VSphere_vmware_cpu_usagemhz_average{host=\"${instance}\", type=\"host\", job=\"local-energy-col-erlc-http\"}",
          "legendFormat": "__auto",
          "range": true,
          "refId": "A"
        },
        {
          "datasource": {
            "type": "prometheus",
            "uid": "Beh5B5B4z"
          },
          "editorMode": "code",
          "expr": "sum(planetary_VSphere_vmware_cpu_usagemhz_average{host=\"${instance}\", type=\"vm\", job=\"local-energy-col-erlc-http\"})",
          "hide": false,
          "legendFormat": "__auto",
          "range": true,
          "refId": "B"
        }
      ],
      "title": "Vsphere Host vs VM CPU",
      "type": "timeseries"
    },
    {
      "datasource": {
        "type": "prometheus",
        "uid": "Beh5B5B4z"
      },
      "fieldConfig": {
        "defaults": {
          "color": {
            "mode": "palette-classic"
          },
          "custom": {
            "axisCenteredZero": false,
            "axisColorMode": "text",
            "axisLabel": "",
            "axisPlacement": "auto",
            "barAlignment": 0,
            "drawStyle": "line",
            "fillOpacity": 25,
            "gradientMode": "none",
            "hideFrom": {
              "legend": false,
              "tooltip": false,
              "viz": false
            },
            "lineInterpolation": "linear",
            "lineWidth": 1,
            "pointSize": 5,
            "scaleDistribution": {
              "type": "linear"
            },
            "showPoints": "auto",
            "spanNulls": false,
            "stacking": {
              "group": "A",
              "mode": "normal"
            },
            "thresholdsStyle": {
              "mode": "off"
            }
          },
          "mappings": [],
          "thresholds": {
            "mode": "absolute",
            "steps": [
              {
                "color": "green"
              },
              {
                "color": "red",
                "value": 80
              }
            ]
          }
        },
        "overrides": []
      },
      "gridPos": {
        "h": 12,
        "w": 9,
        "x": 9,
        "y": 25
      },
      "id": 8,
      "options": {
        "legend": {
          "calcs": [],
          "displayMode": "list",
          "placement": "bottom",
          "showLegend": true
        },
        "tooltip": {
          "mode": "single",
          "sort": "none"
        }
      },
      "targets": [
        {
          "datasource": {
            "type": "prometheus",
            "uid": "Beh5B5B4z"
          },
          "editorMode": "code",
          "expr": "planetary_VSphere_vmware_cpu_usagemhz_average{host=\"${instance}\", type=\"vm\", job=\"local-energy-col-erlc-http\"}",
          "hide": false,
          "legendFormat": "__auto",
          "range": true,
          "refId": "B"
        }
      ],
      "title": "Vsphere VM CPU",
      "type": "timeseries"
    },
    {
      "datasource": {
        "type": "prometheus",
        "uid": "Beh5B5B4z"
      },
      "fieldConfig": {
        "defaults": {
          "color": {
            "mode": "palette-classic"
          },
          "custom": {
            "axisCenteredZero": false,
            "axisColorMode": "text",
            "axisLabel": "",
            "axisPlacement": "auto",
            "barAlignment": 0,
            "drawStyle": "line",
            "fillOpacity": 0,
            "gradientMode": "none",
            "hideFrom": {
              "legend": false,
              "tooltip": false,
              "viz": false
            },
            "lineInterpolation": "linear",
            "lineWidth": 1,
            "pointSize": 5,
            "scaleDistribution": {
              "type": "linear"
            },
            "showPoints": "auto",
            "spanNulls": false,
            "stacking": {
              "group": "A",
              "mode": "none"
            },
            "thresholdsStyle": {
              "mode": "off"
            }
          },
          "mappings": [],
          "thresholds": {
            "mode": "absolute",
            "steps": [
              {
                "color": "green"
              },
              {
                "color": "red",
                "value": 80
              }
            ]
          }
        },
        "overrides": []
      },
      "gridPos": {
        "h": 11,
        "w": 9,
        "x": 0,
        "y": 37
      },
      "id": 16,
      "options": {
        "legend": {
          "calcs": [],
          "displayMode": "list",
          "placement": "bottom",
          "showLegend": true
        },
        "tooltip": {
          "mode": "single",
          "sort": "none"
        }
      },
      "targets": [
        {
          "datasource": {
            "type": "prometheus",
            "uid": "Beh5B5B4z"
          },
          "editorMode": "code",
          "expr": "planetary_VSphere_vmware_mem_consumed_average{host=\"${instance}\", type=\"host\", job=\"local-energy-col-erlc-http\"}",
          "legendFormat": "__auto",
          "range": true,
          "refId": "A"
        },
        {
          "datasource": {
            "type": "prometheus",
            "uid": "Beh5B5B4z"
          },
          "editorMode": "code",
          "expr": "sum(planetary_VSphere_vmware_mem_consumed_average{host=\"${instance}\", type=\"vm\", job=\"local-energy-col-erlc-http\"})",
          "hide": false,
          "legendFormat": "__auto",
          "range": true,
          "refId": "B"
        }
      ],
      "title": "Vsphere Host vs VM Memory",
      "type": "timeseries"
    },
    {
      "datasource": {
        "type": "prometheus",
        "uid": "Beh5B5B4z"
      },
      "fieldConfig": {
        "defaults": {
          "color": {
            "mode": "palette-classic"
          },
          "custom": {
            "axisCenteredZero": false,
            "axisColorMode": "text",
            "axisLabel": "",
            "axisPlacement": "auto",
            "barAlignment": 0,
            "drawStyle": "line",
            "fillOpacity": 25,
            "gradientMode": "none",
            "hideFrom": {
              "legend": false,
              "tooltip": false,
              "viz": false
            },
            "lineInterpolation": "linear",
            "lineWidth": 1,
            "pointSize": 5,
            "scaleDistribution": {
              "type": "linear"
            },
            "showPoints": "auto",
            "spanNulls": false,
            "stacking": {
              "group": "A",
              "mode": "normal"
            },
            "thresholdsStyle": {
              "mode": "off"
            }
          },
          "mappings": [],
          "thresholds": {
            "mode": "absolute",
            "steps": [
              {
                "color": "green"
              },
              {
                "color": "red",
                "value": 80
              }
            ]
          }
        },
        "overrides": []
      },
      "gridPos": {
        "h": 11,
        "w": 9,
        "x": 9,
        "y": 37
      },
      "id": 17,
      "options": {
        "legend": {
          "calcs": [],
          "displayMode": "list",
          "placement": "bottom",
          "showLegend": true
        },
        "tooltip": {
          "mode": "single",
          "sort": "none"
        }
      },
      "targets": [
        {
          "datasource": {
            "type": "prometheus",
            "uid": "Beh5B5B4z"
          },
          "editorMode": "code",
          "expr": "planetary_VSphere_vmware_mem_consumed_average{host=\"${instance}\", type=\"vm\", job=\"local-energy-col-erlc-http\"}",
          "hide": false,
          "legendFormat": "__auto",
          "range": true,
          "refId": "B"
        }
      ],
      "title": "Vsphere VM Memory",
      "type": "timeseries"
    },
    {
      "datasource": {
        "type": "prometheus",
        "uid": "Beh5B5B4z"
      },
      "fieldConfig": {
        "defaults": {
          "color": {
            "mode": "palette-classic"
          },
          "custom": {
            "axisCenteredZero": false,
            "axisColorMode": "text",
            "axisLabel": "",
            "axisPlacement": "auto",
            "barAlignment": 0,
            "drawStyle": "line",
            "fillOpacity": 0,
            "gradientMode": "none",
            "hideFrom": {
              "legend": false,
              "tooltip": false,
              "viz": false
            },
            "lineInterpolation": "linear",
            "lineWidth": 1,
            "pointSize": 5,
            "scaleDistribution": {
              "type": "linear"
            },
            "showPoints": "auto",
            "spanNulls": false,
            "stacking": {
              "group": "A",
              "mode": "none"
            },
            "thresholdsStyle": {
              "mode": "off"
            }
          },
          "mappings": [],
          "thresholds": {
            "mode": "absolute",
            "steps": [
              {
                "color": "green"
              },
              {
                "color": "red",
                "value": 80
              }
            ]
          }
        },
        "overrides": []
      },
      "gridPos": {
        "h": 11,
        "w": 9,
        "x": 0,
        "y": 48
      },
      "id": 18,
      "options": {
        "legend": {
          "calcs": [],
          "displayMode": "list",
          "placement": "bottom",
          "showLegend": true
        },
        "tooltip": {
          "mode": "single",
          "sort": "none"
        }
      },
      "targets": [
        {
          "datasource": {
            "type": "prometheus",
            "uid": "Beh5B5B4z"
          },
          "editorMode": "code",
          "expr": "planetary_VSphere_vmware_net_usage_average{host=\"${instance}\", type=\"host\", job=\"local-energy-col-erlc-http\"}",
          "legendFormat": "__auto",
          "range": true,
          "refId": "A"
        },
        {
          "datasource": {
            "type": "prometheus",
            "uid": "Beh5B5B4z"
          },
          "editorMode": "code",
          "expr": "sum(planetary_VSphere_vmware_net_usage_average{host=\"${instance}\", type=\"vm\", job=\"local-energy-col-erlc-http\"})",
          "hide": false,
          "legendFormat": "__auto",
          "range": true,
          "refId": "B"
        }
      ],
      "title": "Vsphere Host vs VM Network",
      "type": "timeseries"
    },
    {
      "datasource": {
        "type": "prometheus",
        "uid": "Beh5B5B4z"
      },
      "fieldConfig": {
        "defaults": {
          "color": {
            "mode": "palette-classic"
          },
          "custom": {
            "axisCenteredZero": false,
            "axisColorMode": "text",
            "axisLabel": "",
            "axisPlacement": "auto",
            "barAlignment": 0,
            "drawStyle": "line",
            "fillOpacity": 25,
            "gradientMode": "none",
            "hideFrom": {
              "legend": false,
              "tooltip": false,
              "viz": false
            },
            "lineInterpolation": "linear",
            "lineWidth": 1,
            "pointSize": 5,
            "scaleDistribution": {
              "type": "linear"
            },
            "showPoints": "auto",
            "spanNulls": false,
            "stacking": {
              "group": "A",
              "mode": "normal"
            },
            "thresholdsStyle": {
              "mode": "off"
            }
          },
          "mappings": [],
          "thresholds": {
            "mode": "absolute",
            "steps": [
              {
                "color": "green"
              },
              {
                "color": "red",
                "value": 80
              }
            ]
          }
        },
        "overrides": []
      },
      "gridPos": {
        "h": 11,
        "w": 9,
        "x": 9,
        "y": 48
      },
      "id": 19,
      "options": {
        "legend": {
          "calcs": [],
          "displayMode": "list",
          "placement": "bottom",
          "showLegend": true
        },
        "tooltip": {
          "mode": "single",
          "sort": "none"
        }
      },
      "targets": [
        {
          "datasource": {
            "type": "prometheus",
            "uid": "Beh5B5B4z"
          },
          "editorMode": "code",
          "expr": "planetary_VSphere_vmware_net_usage_average{host=\"${instance}\", type=\"vm\", job=\"local-energy-col-erlc-http\"}",
          "hide": false,
          "legendFormat": "__auto",
          "range": true,
          "refId": "B"
        }
      ],
      "title": "Vsphere VM Network",
      "type": "timeseries"
    },
    {
      "datasource": {
        "type": "prometheus",
        "uid": "Beh5B5B4z"
      },
      "fieldConfig": {
        "defaults": {
          "color": {
            "mode": "palette-classic"
          },
          "custom": {
            "axisCenteredZero": false,
            "axisColorMode": "text",
            "axisLabel": "",
            "axisPlacement": "auto",
            "barAlignment": 0,
            "drawStyle": "line",
            "fillOpacity": 0,
            "gradientMode": "none",
            "hideFrom": {
              "legend": false,
              "tooltip": false,
              "viz": false
            },
            "lineInterpolation": "linear",
            "lineWidth": 1,
            "pointSize": 5,
            "scaleDistribution": {
              "type": "linear"
            },
            "showPoints": "auto",
            "spanNulls": false,
            "stacking": {
              "group": "A",
              "mode": "none"
            },
            "thresholdsStyle": {
              "mode": "off"
            }
          },
          "mappings": [],
          "thresholds": {
            "mode": "absolute",
            "steps": [
              {
                "color": "green"
              },
              {
                "color": "red",
                "value": 80
              }
            ]
          }
        },
        "overrides": []
      },
      "gridPos": {
        "h": 17,
        "w": 18,
        "x": 0,
        "y": 59
      },
      "id": 20,
      "options": {
        "legend": {
          "calcs": [],
          "displayMode": "list",
          "placement": "bottom",
          "showLegend": true
        },
        "tooltip": {
          "mode": "single",
          "sort": "none"
        }
      },
      "targets": [
        {
          "datasource": {
            "type": "prometheus",
            "uid": "Beh5B5B4z"
          },
          "editorMode": "code",
          "expr": "planetary_VSphere_vmware_power_power_average{host=\"${instance}\", type=\"host\", job=\"local-energy-col-erlc-http\"}",
          "legendFormat": "__auto",
          "range": true,
          "refId": "A"
        },
        {
          "datasource": {
            "type": "prometheus",
            "uid": "Beh5B5B4z"
          },
          "editorMode": "code",
          "expr": "planetary_VSphere_vmware_cpu_usagemhz_average{host=\"${instance}\", type=\"host\", job=\"local-energy-col-erlc-http\"}",
          "hide": true,
          "legendFormat": "__auto",
          "range": true,
          "refId": "B"
        },
        {
          "datasource": {
            "type": "prometheus",
            "uid": "Beh5B5B4z"
          },
          "editorMode": "code",
          "expr": "sum(planetary_VSphere_vmware_cpu_usagemhz_average{host=\"${instance}\", type=\"vm\", job=\"local-energy-col-erlc-http\"}) * ${cpuMhzFactor} + ${hostPowerOffset}",
          "hide": false,
          "legendFormat": "__auto",
          "range": true,
          "refId": "C"
        }
      ],
      "title": "Power vs CPU usage",
      "type": "timeseries"
    }
  ],
  "refresh": "5s",
  "revision": 1,
  "schemaVersion": 38,
  "style": "dark",
  "tags": [],
  "templating": {
    "list": [
      {
        "current": {
          "selected": false,
          "text": "deerls6vh313.siemens.net",
          "value": "deerls6vh313.siemens.net"
        },
        "datasource": {
          "type": "prometheus",
          "uid": "Beh5B5B4z"
        },
        "definition": "planetary_VSphere_vmware_power_power_average{type=\"host\"}",
        "hide": 0,
        "includeAll": false,
        "multi": false,
        "name": "instance",
        "options": [],
        "query": {
          "query": "planetary_VSphere_vmware_power_power_average{type=\"host\"}",
          "refId": "StandardVariableQuery"
        },
        "refresh": 1,
        "regex": "/host=\"(?<text>[^\"]+)/g",
        "skipUrlSync": false,
        "sort": 0,
        "type": "query"
      },
      {
        "current": {
          "selected": false,
          "text": "0.0024",
          "value": "0.0024"
        },
        "hide": 0,
        "name": "cpuMhzFactor",
        "options": [
          {
            "selected": true,
            "text": "0.0024",
            "value": "0.0024"
          }
        ],
        "query": "0.0024",
        "skipUrlSync": false,
        "type": "textbox"
      },
      {
        "current": {
          "selected": false,
          "text": "0",
          "value": "0"
        },
        "hide": 0,
        "name": "hostPowerOffset",
        "options": [
          {
            "selected": true,
            "text": "0",
            "value": "0"
          }
        ],
        "query": "0",
        "skipUrlSync": false,
        "type": "textbox"
      }
    ]
  },
  "time": {
    "from": "now-1h",
    "to": "now"
  },
  "timepicker": {},
  "timezone": "",
  "title": "Vsphere",
  "uid": "8zAAuEfVz",
  "version": 38,
  "weekStart": ""
}